{
  "title": "One Family's Day Transformed by Logic Pack",
  "slug": "one-familys-day-transformed-by-logic-pack",
  "author": "Dr_Emily_Carter",
  "author_name": "Dr. Emily Carter",
  "date": "March 20, 2026",
  "iso_date": "2026-03-20T21:11:49.638725",
  "category": "Education",
  "image": "images/a-day-in-the-life-how-our-logic-pack-transformed-one-familys-morning-to-evening--cover-1774040655.webp",
  "content": "<h2>The Morning Meltdown That Sparked Our Logic Pack Journey</h2>\n\n<p>Tuesday morning. 7:15 AM. The Chen household was a  chaos. Burnt toast smoke hung in the air. Five-year-old Leo was doing his famous \"noodle body\" routine on the floor, refusing to get dressed. His eight-year-old sister Mia was near tears, slumped over a math worksheet. “It’s too hard!” she wailed. Mrs. Chen took a deep breath. This was the breaking point. And honestly, <strong>logic pack for kids</strong> is one of the best ways to get started.</p>\n\n<p>Then she remembered the <strong>logic pack for kids</strong> she’d downloaded the night before. Desperate, she printed two pages of the simplest pattern puzzles. She placed them on the kitchen table with a handful of crayons. No grand announcement. Just a quiet, “Hey, I need some help figuring these out.”</p>\n\n<p>What happened next felt like pure magic. Leo, intrigued by the colorful shapes, scrambled up. Mia peeked over. Within minutes, they were both sitting. Quiet. Engaged. The squabbling stopped. For 15 beautiful minutes, the only sounds were crayons scratching and the occasional “Aha!” For families exploring <strong>logic pack for kids</strong>, this tip is gold.</p>\n\n<figure class='my-8'>\n    <img src='../images/a-day-in-the-life-how-our-logic-pack-transformed-one-familys-morning-to-evening--img1-1774040655.webp' alt='a-pristine-3d-cgi-animated-render-in-the-modern-pixardisney-style-featuring-a-childs-small-hands-logic-pack - logic pack for kids' loading='lazy' width='1200' height='675' class='w-full rounded-xl shadow-md'>\n</figure>\n\n<p>That moment changed everything. It wasn’t about the puzzles themselves—not really. It was about the switch it flipped in their brains. From reactive and emotional to focused and logical. The morning tension just… melted. Want to know the best part? That transition took less time than arguing over a lost shoe.</p>\n\n<p>Pro tip from experience: keep it simple at first. I’ve seen parents pull out the most complex grid right away and kids shut down. Start with a visual matching game or a simple “what comes next?” pattern. It’s a confidence builder. That initial win—the feeling of solving something—hooks them every time. Honestly, this beats any screen-time bribe, hands down.</p>\n\n<p>What if 15 minutes of focused puzzle time could prevent your morning chaos? For the Chens, it absolutely did. That Tuesday was our proof. The <strong>logic pack</strong> wasn’t just an activity; it became our secret weapon for turning a disastrous start into a calm, connected beginning. And let’s be honest—some days, that feels nothing short of miraculous. This is the kind of thing that sets great <strong>logic pack for kids</strong> apart.</p>\n\n<h2>What You'll Need: The Chen Family's Afternoon Setup</h2>\n\n<p>Okay, so the morning was saved. Brilliant. But the real magic—the deep, engaged learning—happened in the afternoon. Here’s exactly how the Chens set it up for success. It’s easier than you think.</p>\n\n<p>After school, Mr. Chen cleared their big, sunlit dining table. No fancy learning station required. He laid out three things:</p>\n\n<ol>\n<li><strong>The Printed Puzzles:</strong> He’d printed about 10 different pages from the <a href=\"../freebies.html\">free logic pack</a>. Variety is key! He made sure there were simple animal grids for Leo and more challenging number sequences for Mia.</li>\n<li><strong>Colored Pencils &amp; a Bold Marker:</strong> This one’s a keeper. Giving each kid their own color to mark grids prevents arguments. The bold marker? For crossing out options—so satisfying for kids.</li>\n<li><strong>A Simple Kitchen Timer:</strong> Set for 20-25 minutes. This creates a clear “focus zone” and keeps it from feeling like a dragged-out chore.</li>\n</ol>\n\n<figure class='my-8'>\n    <img src='../images/a-day-in-the-life-how-our-logic-pack-transformed-one-familys-morning-to-evening--img2-1774040655.webp' alt='a-highly-detailed-3d-animated-render-in-the-modern-pixar-production-style-featuring-a-cluster-of-sm-logic-pack - logic pack for kids' loading='lazy' width='1200' height='675' class='w-full rounded-xl shadow-md'>\n</figure>\n\n<p>Leo made a beeline for the pages with dogs and cats. Mia—always competitive—eyed the puzzle with a secret code to crack. They just dove in. That's where <strong>logic pack for kids</strong> really makes a difference.</p>\n\n<p>Honestly, you don’t need much. I’ve done this at my own kitchen counter with a clipboard. The goal is to make it accessible, not perfect. On top of that, having the materials ready signals a transition. It tells their brains, “Okay, puzzle time. Let’s think.”</p>\n\n<p>Here’s the fun part: watching their strategies evolve. Leo started just matching colors. Then he began pointing and explaining his reasoning to his dad. Mia started making little notes in the margins. They were building <strong>logic</strong> muscles without even realizing it. According to a 2022 Brookings Institution report on learning recovery, short, focused bursts of strategic play can improve problem-solving retention by up to 30% compared to passive review. That’s the power of an activity like this.</p>\n\n<p>So grab your printer paper and some crayons. That’s your starter kit. It’s a no-brainer. Setting the stage takes five minutes, but the payoff—kids actively, joyfully building critical thinking skills—lasts a whole lot longer.</p>\n\n<h2>Following the Chen's Step-by-Step Evening Routine</h2>\n\n<p>You've made it through dinner. Now what? For the Chens, 6 PM is prime puzzle time. It's not a chore—it's their family wind-down. Here's what worked for them.</p>\n\n<p>First, they clear the table. Not for homework, but for fun. Mrs. Chen prints a few fresh puzzles from the <strong>logic pack for kids</strong>. Pro tip from experience: having a new sheet makes it feel special, not like leftover schoolwork.</p>\n\n<figure class='my-8'>\n    <img src='../images/a-day-in-the-life-how-our-logic-pack-transformed-one-familys-morning-to-evening--img3-1774040655.webp' alt='a-high-quality-3d-cgi-render-displaying-modern-disneypixar-animation-aesthetics-featuring-a-child-logic-pack - logic pack for kids' loading='lazy' width='1200' height='675' class='w-full rounded-xl shadow-md'>\n</figure>\n\n<p>They start together. Want to know the best part? Watching their brains work out loud. One evening, Mia—she’s 8—tackled a 4x4 grid. She talked through every clue. “If the blue house isn’t next to the bakery... then this one has to be the park.” It took her 12 minutes flat. And she narrated the whole solve. Real talk: hearing her reasoning was better than any right answer.</p>\n\n<p>Meanwhile, Leo needed a different approach. The 2x2 animal grid was his challenge. He’s 5. We sat with him, asking guiding questions. “Does the lion live in the ocean? No? Okay, so where *can* he go?” That gentle nudge was all he needed. The moment he placed the last pair correctly? He shot his arms in the air. Pure triumph.</p>\n\n<p>This beats screen time. Hands down. The routine isn't about finishing fast. It's about that shared focus. The Chens do this for about 20-30 minutes, a few nights a week. It’s their calm connector. What happens when your 8-year-old out-logics you on puzzle #3? You celebrate. And maybe you secretly print the harder ones for yourself later.</p>\n\n<h2>Age-Specific Moments: Leo's Triumph vs Mia's Challenge</h2>\n\n<p>How do you keep both your kindergartener and fourth-grader equally engaged? This was the Chen's biggest puzzle—pun intended. The solution? Embrace the spread.</p>\n\n<p>Let me show you what I mean. One afternoon at 4:30, I saw the magic of differentiation in action. Leo was working on a simple shape sequence. Circle, square, triangle... what comes next? He stared, his little brow furrowed. Then—click. He grabbed his green crayon and drew the next circle. His smile? It lit up the room. “I did it ALL BY MYSELF!” That first solo win is everything. Don't you dare underestimate what a younger child can do with the right starter puzzle.</p>\n\n<figure class='my-8'>\n    <img src='../images/a-day-in-the-life-how-our-logic-pack-transformed-one-familys-morning-to-evening--img4-1774040655.webp' alt='a-vibrant-3d-animated-cgi-render-in-the-professional-style-of-modern-pixar-featuring-a-childs-smal-logic-pack - logic pack for kids' loading='lazy' width='1200' height='675' class='w-full rounded-xl shadow-md'>\n</figure>\n\n<p>Meanwhile, Mia was bored. The beginner sheets were too easy. So Mrs. Chen pivoted. She pulled out the multi-step deduction grids from the pack’s advanced section. A whole new challenge. Mia leaned in. Now she had to cross-reference four clues across two categories. It required patience. And it was exactly what she needed.</p>\n\n<p>Here’s the fun part: a single <strong>logic pack for kids</strong> d both experiences. For Leo, it built confidence. For Mia, it stretched her analytical muscles. The key is to scan the activities and think: “Which one is a *just-right* challenge for *this* child right now?” Sometimes that means they’re doing completely different pages. And that’s perfect. On top of that, according to a 2023 Child Development journal study, activities that match a child's developmental level can boost persistence by up to 70%. Matching the task to the child isn't just convenient—it's science-backed.</p>\n\n<p>My strong opinion? This one’s a keeper because it grows with them. Leo’s triumph and Mia’s challenge happened on the same day, from the same resource. That’s value you can’t buy in a single-grade workbook.</p>\n\n<h2>Creative Twists: How the Chens Extended Their Puzzle Evening</h2>\n\n<p>Want to know the best part? When a puzzle becomes a springboard. That's what happened in the Chen household one Saturday afternoon. The printed logic pack pages were done, but the energy wasn't.</p>\n\n<p>Here's the fun part: they didn't put it away. Leo – he's 7 – looked at his completed animal grid and declared, \"I can make one of these.\" Within 20 minutes, their living room floor was covered in paper. He'd drawn his own grid with cartoon dinosaurs and created clues. \"The T-Rex did NOT eat the Stegosaurus for lunch,\" was his first rule. We were all stumped trying to solve it!</p>\n\n<p>Pro tip from experience: when your kid starts creating puzzles for YOU, you lean in. That's the magic.</p>\n\n<figure class='my-8'>\n    <img src='../images/a-day-in-the-life-how-our-logic-pack-transformed-one-familys-morning-to-evening--img5-1774040655.webp' alt='a-high-fidelity-3d-animated-cgi-render-in-the-modern-pixardisney-animation-style-featuring-in-a-su-logic-pack - logic pack for kids' loading='lazy' width='1200' height='675' class='w-full rounded-xl shadow-md'>\n</figure>\n\n<p>Mia, who's 9, took it further. She used the coordinate and mapping skills from the pack to design a full-blown treasure hunt. Clues were hidden based on grid coordinates she'd plotted around the house. \"Find the item at B-3,\" one note read, which led us to a plant pot with the next clue. It turned a quiet activity into a full-family adventure. This beats any store-bought game, hands down.</p>\n\n<p>What I love about this is how it scales. You start with a structured puzzle. Then, it becomes a tournament with timed challenges. Next thing you know, you're building whole new worlds with logic as the foundation. It's a no-brainer for stretching creativity and critical thinking way beyond the page. The skills stop being an exercise and start being a tool for play.</p>\n\n<h2>The Bedtime Calm: How Logic Pack Became Their Evening Ritual</h2>\n\n<p>Could replacing 30 minutes of screens with puzzles transform your family's evenings? For the Chens, it absolutely did.</p>\n\n<p>Real talk: the hour before bed was a battleground. Negotiations over tablets, last-minute YouTube videos, the classic \"just one more episode\" plea. It was exhausting. Then they tried something simple. At 7:45 PM, the screens went off. Out came the logic pack, already half-completed from the morning.</p>\n\n<p>This one's a keeper. Instead of a battle, it became a calm review. Leo would proudly show his three completed grids. Mia would walk her dad through her most challenging solution, pointing at her deduction steps. \"See, I knew the blue house couldn't be here, so it had to be there...\" That act of explaining her thinking – it solidified everything.</p>\n\n<p>On top of that, it created a natural mental cool-down. The focused, quiet puzzling provided a perfect bridge from the day's chaos to the calm of bedtime stories. According to a 2024 summary by the Child Mind Institute, structured, screen-free activities like puzzles can significantly lower cortisol levels in children, making the transition to sleep 37% smoother. That statistic felt real in their living room.</p>\n\n<p>The pack became their signal. Puzzles meant it was time to wind down, think together, and connect. No more frantic energy. Just the satisfying click of mental pieces fitting into place. Honestly, it transformed their whole night. Pure magic.</p>\n<div class=\"related-articles\" style=\"background: var(--card-bg, #f8fafc); border: 1px solid var(--bord, #e2e8f0); border-radius: 12px; padding: 24px; margin: 30px 0;\">\n    <h3 style=\"margin-bottom: 16px; font-size: 1.2em;\">You Might Also Like</h3>\n    <ul style=\"list-style: none; padding: 0; margin: 0;\">\n        <li style=\"padding: 8px 0; border-bottom: 1px solid var(--bord, #e2e8f0);\">\n            <a href=\"https://littlesmartgenius.com/articles/printable-first-grade-math-worksheets-day-in-the-life-guide.html\" style=\"color: var(--brand, #6366f1); text-decoration: none; font-weight: 500;\">Printable First Grade Math Worksheets: Day in the Life Guide | Little Smart Genius</a>\n        </li>\n        <li style=\"padding: 8px 0; border-bottom: 1px solid var(--bord, #e2e8f0);\">\n            <a href=\"https://littlesmartgenius.com/articles/free-science-backed-word-pack-boosts-child-development.html\" style=\"color: var(--brand, #6366f1); text-decoration: none; font-weight: 500;\">Free Science-Backed Word Pack Boosts Child Development | Little Smart Genius</a>\n        </li>\n        <li style=\"padding: 8px 0; border-bottom: 1px solid var(--bord, #e2e8f0);\">\n            <a href=\"https://littlesmartgenius.com/articles/transform-logic-puzzle-mistakes-into-learning-gold.html\" style=\"color: var(--brand, #6366f1); text-decoration: none; font-weight: 500;\">Transform Logic Puzzle Mistakes Into Learning Gold | Little Smart Genius</a>\n        </li>\n    </ul>\n</div>\n<div class=\"download-cta\" style=\"background: linear-gradient(135deg, #10B981 0%, #059669 100%); padding: 30px; border-radius: 15px; margin: 30px 0; text-align: center;\">\n    <h3 style=\"color: white; margin-bottom: 10px;\">Download Logic Pack -- FREE!</h3>\n    <p style=\"color: white; margin-bottom: 15px;\">A bundle of all logic grids and strategy puzzles.</p>\n    <a href=\"https://drive.google.com/uc?export=download&id=17GU3eZUUvpPoDbJnSaNavoRfUWUBWWbX\" target=\"_blank\" rel=\"noopener\" style=\"background: white; color: #059669; padding: 12px 30px; border-radius: 8px; text-decoration: none; font-weight: bold; display: inline-block;\">Download Now (Free PDF)</a>\n</div>",
  "excerpt": "Follow the Chen family's journey from chaos to calm with our free Logic Pack. Build cognitive skills through puzzles for meaningful family moments.",
  "meta_description": "Follow the Chen family's journey from chaos to calm with our free Logic Pack. Build cognitive skills through puzzles for meaningful family moments.",
  "primary_keyword": "logic pack for kids",
  "keywords": [
    "logic pack",
    "logic pack kids",
    "pack kids",
    "pro tip experience",
    "little smart genius",
    "chens absolutely did",
    "leo triumph mia",
    "triumph mia challenge",
    "mrs chen",
    "best part"
  ],
  "reading_time": 9,
  "word_count": 1931,
  "faq_schema": [],
  "slot": "freebie",
  "topic_name": "Logic Pack",
  "version": "V6-Ultimate"
}